d_flipflop/d_flipflop.v
module d_flipflop (
    input clk,
    input reset,
    input d,
    output reg q
);
always @(posedge clk) begin
    if(reset) q<=0;
    else q <= d;
    
end
endmodule

d_flipflop/d_flipflop_tb.v
`timescale 1ns/1ps

module d_flipflop_tb;
reg d, clk,reset;
wire q;

d_flipflop uut(
    .d(d),
    .clk(clk),
    .reset(reset),
    .q(q)
);

always #5 clk = ~clk;  // Toggle clock every 5 ns

initial begin
    $dumpfile("d_flipflop.vcd");
    $dumpvars(0, d_flipflop_tb);  // Corrected this line

    d = 0;
    clk = 0;
    reset =0;

    #10;
    d = 1;

    #40;
    d = 0;

    #20;
    d = 1;
    reset=1;
    #20;
    reset=0;
    #20;
    $finish;  // Added missing semicolon
end
endmodule

d_flipflop/d_flipflop.vcd
$date
	Wed Jul 02 20:36:11 2025
$end
$version
	Icarus Verilog
$end
$timescale
	1ps
$end
$scope module d_flipflop_tb $end
$var wire 1 ! q $end
$var reg 1 " clk $end
$var reg 1 # d $end
$var reg 1 $ reset $end
$scope module uut $end
$var wire 1 " clk $end
$var wire 1 # d $end
$var wire 1 $ reset $end
$var reg 1 ! q $end
$upscope $end
$upscope $end
$enddefinitions $end
$comment Show the parameter values. $end
$dumpall
$end
#0
$dumpvars
0$
0#
0"
x!
$end
#5000
0!
1"
#10000
0"
1#
#15000
1!
1"
#20000
0"
#25000
1"
#30000
0"
#35000
1"
#40000
0"
#45000
1"
#50000
0"
0#
#55000
0!
1"
#60000
0"
#65000
1"
#70000
0"
1$
1#
#75000
1"
#80000
0"
#85000
1"
#90000
0"
0$
#95000
1!
1"
