counter/simple_counter.v
module simple_counter (
    input clk,
    input rst,
    output reg [31:0] count
);

always @(posedge clk) begin
    if (rst)
        count <= 32'b0;
    else
        count <= count + 1;
end

endmodule

counter/simple_counter_tb.v
`timescale 1ns/1ps

module simple_counter_tb;

reg clk, rst;
wire [31:0] count;

simple_counter uut (
    .clk(clk),
    .rst(rst),
    .count(count)
);

// Clock generation
always #5 clk = ~clk;

initial begin
    $dumpfile("counter.vcd");
    $dumpvars(0, simple_counter_tb);

    // Initial values
    clk = 0;
    rst = 1;
    #15;

    rst = 0;   // Release reset
    #100;

    rst = 1;   // Apply reset again
    #10;

    rst = 0;   // Release reset
    #50;

    $finish;
end

endmodule

counter/counter.vcd
$date
	Fri Jun 27 17:31:01 2025
$end
$version
	Icarus Verilog
$end
$timescale
	1ps
$end
$scope module simple_counter_tb $end
$var wire 32 ! count [31:0] $end
$var reg 1 " clk $end
$var reg 1 # rst $end
$scope module uut $end
$var wire 1 " clk $end
$var wire 1 # rst $end
$var reg 32 $ count [31:0] $end
$upscope $end
$upscope $end
$enddefinitions $end
$comment Show the parameter values. $end
$dumpall
$end
#0
$dumpvars
bx $
1#
0"
bx !
$end
#5000
b0 !
b0 $
1"
#10000
0"
#15000
b1 !
b1 $
1"
0#
#20000
0"
#25000
b10 !
b10 $
1"
#30000
0"
#35000
b11 !
b11 $
1"
#40000
0"
#45000
b100 !
b100 $
1"
#50000
0"
#55000
b101 !
b101 $
1"
#60000
0"
#65000
b110 !
b110 $
1"
#70000
0"
#75000
b111 !
b111 $
1"
#80000
0"
#85000
b1000 !
b1000 $
1"
#90000
0"
#95000
b1001 !
b1001 $
1"
#100000
0"
#105000
b1010 !
b1010 $
1"
#110000
0"
#115000
b0 !
b0 $
1"
1#
#120000
0"
#125000
b1 !
b1 $
1"
0#
#130000
0"
#135000
b10 !
b10 $
1"
#140000
0"
#145000
b11 !
b11 $
1"
#150000
0"
#155000
b100 !
b100 $
1"
#160000
0"
#165000
b101 !
b101 $
1"
#170000
0"
#175000
b110 !
b110 $
1"
