decoder/decoder.v
module decoder3x8 (
  input  [2:0] in,
  output [7:0] out
);

// Set the output bit corresponding to input value high (one-hot encoding)
assign out = 1 << in;


endmodule

decoder/decoder_tb.v
`timescale 1ns/1ps
module decoder3x8_tb;
reg [2:0]in;
wire [7:0]out;

decoder3x8 uut(
    .in(in),
    .out(out)
);

initial begin
    $dumpfile("decoder3x8.vcd");
    $dumpvars(0,decoder3x8_tb);
end

initial begin
    $monitor("Time =%0t | in =%b | out =%b",$time,in,out);
end

initial begin
      in = 3'b000; #10;
    in = 3'b001; #10;
    in = 3'b010; #10;
    in = 3'b011; #10;
    in = 3'b100; #10;
    in = 3'b101; #10;
    in = 3'b110; #10;
    in = 3'b111; #10;
    $finish;
end
endmodule

decoder/decoder3x8.vcd
$date
	Mon Jun 30 22:59:42 2025
$end
$version
	Icarus Verilog
$end
$timescale
	1ps
$end
$scope module decoder3x8_tb $end
$var wire 8 ! out [7:0] $end
$var reg 3 " in [2:0] $end
$scope module uut $end
$var wire 3 # in [2:0] $end
$var wire 8 $ out [7:0] $end
$upscope $end
$upscope $end
$enddefinitions $end
$comment Show the parameter values. $end
$dumpall
$end
#0
$dumpvars
b1 $
b0 #
b0 "
b1 !
$end
#10000
b10 !
b10 $
b1 "
b1 #
#20000
b100 !
b100 $
b10 "
b10 #
#30000
b1000 !
b1000 $
b11 "
b11 #
#40000
b10000 !
b10000 $
b100 "
b100 #
#50000
b100000 !
b100000 $
b101 "
b101 #
#60000
b1000000 !
b1000000 $
b110 "
b110 #
#70000
b10000000 !
b10000000 $
b111 "
b111 #
