up_down_counter/up_down_counter.v
// === Module ===
module up_down_counter (
   input mode,
   input clr,
   input ld,
   input [7:0] d_in,
   input clk,
   output reg [7:0] count
);

always @(posedge clk) begin
    if (ld) count <= d_in;
    else if (clr) count <= 0;
    else if (mode) count <= count + 1;
    else count <= count - 1;
end

endmodule

up_down_counter/up_down_counter_tb.v
`timescale 1ns/1ps

module up_down_counter_tb;
reg [7:0] d_in;
reg mode, clr, clk, ld;
wire [7:0] count;

up_down_counter uut (
    .mode(mode),
    .clr(clr),
    .ld(ld),
    .d_in(d_in),
    .clk(clk),
    .count(count)
);

// Fixed signal name from `clock` to `clk`
always #5 clk = ~clk;

initial begin
    $dumpfile("up_down_counter.vcd");
    $dumpvars(0, up_down_counter_tb);

    // Initialize
    clk = 0;
    clr = 1;
    ld = 0;
    mode = 0;
    d_in = 8'd1;

    #10;
    clr = 0;
    ld = 1;

    #10;
    ld = 0;

    // Count up
    mode = 1;
    #40;

    // Count down
    mode = 0;
    #40;

    $finish;
end
endmodule

up_down_counter/up_down_counter.vcd
$date
	Wed Jul 02 12:32:30 2025
$end
$version
	Icarus Verilog
$end
$timescale
	1ps
$end
$scope module up_down_counter_tb $end
$var wire 8 ! count [7:0] $end
$var reg 1 " clk $end
$var reg 1 # clr $end
$var reg 8 $ d_in [7:0] $end
$var reg 1 % ld $end
$var reg 1 & mode $end
$scope module uut $end
$var wire 1 " clk $end
$var wire 1 # clr $end
$var wire 8 ' d_in [7:0] $end
$var wire 1 % ld $end
$var wire 1 & mode $end
$var reg 8 ( count [7:0] $end
$upscope $end
$upscope $end
$enddefinitions $end
$comment Show the parameter values. $end
$dumpall
$end
#0
$dumpvars
bx (
b1 '
0&
0%
b1 $
1#
0"
bx !
$end
#5000
b0 !
b0 (
1"
#10000
0"
1%
0#
#15000
b1 !
b1 (
1"
#20000
0"
1&
0%
#25000
b10 !
b10 (
1"
#30000
0"
#35000
b11 !
b11 (
1"
#40000
0"
#45000
b100 !
b100 (
1"
#50000
0"
#55000
b101 !
b101 (
1"
#60000
0"
0&
#65000
b100 !
b100 (
1"
#70000
0"
#75000
b11 !
b11 (
1"
#80000
0"
#85000
b10 !
b10 (
1"
#90000
0"
#95000
b1 !
b1 (
1"
